{"nodes": [{"id": "registry", "label": "registry.go", "file_type": "code", "source_file": "internal\\capability\\registry.go", "source_location": "L1"}, {"id": "capability_scopetype", "label": "ScopeType", "file_type": "code", "source_file": "internal\\capability\\registry.go", "source_location": "L9"}, {"id": "capability_profilerecord", "label": "ProfileRecord", "file_type": "code", "source_file": "internal\\capability\\registry.go", "source_location": "L17"}, {"id": "capability_loader", "label": "Loader", "file_type": "code", "source_file": "internal\\capability\\registry.go", "source_location": "L25"}, {"id": "capability_registry", "label": "Registry", "file_type": "code", "source_file": "internal\\capability\\registry.go", "source_location": "L29"}, {"id": "registry_newregistry", "label": "NewRegistry()", "file_type": "code", "source_file": "internal\\capability\\registry.go", "source_location": "L33"}, {"id": "capability_registry_surface", "label": ".Surface()", "file_type": "code", "source_file": "internal\\capability\\registry.go", "source_location": "L37"}, {"id": "registry_applyprofilerecord", "label": "applyProfileRecord()", "file_type": "code", "source_file": "internal\\capability\\registry.go", "source_location": "L78"}, {"id": "registry_clonecapabilityset", "label": "cloneCapabilitySet()", "file_type": "code", "source_file": "internal\\capability\\registry.go", "source_location": "L88"}], "edges": [{"source": "registry", "target": "context", "relation": "imports_from", "confidence": "EXTRACTED", "source_file": "internal\\capability\\registry.go", "source_location": "L4", "weight": 1.0}, {"source": "registry", "target": "domain", "relation": "imports_from", "confidence": "EXTRACTED", "source_file": "internal\\capability\\registry.go", "source_location": "L6", "weight": 1.0}, {"source": "registry", "target": "capability_scopetype", "relation": "contains", "confidence": "EXTRACTED", "source_file": "internal\\capability\\registry.go", "source_location": "L9", "weight": 1.0}, {"source": "registry", "target": "capability_profilerecord", "relation": "contains", "confidence": "EXTRACTED", "source_file": "internal\\capability\\registry.go", "source_location": "L17", "weight": 1.0}, {"source": "registry", "target": "capability_loader", "relation": "contains", "confidence": "EXTRACTED", "source_file": "internal\\capability\\registry.go", "source_location": "L25", "weight": 1.0}, {"source": "registry", "target": "capability_registry", "relation": "contains", "confidence": "EXTRACTED", "source_file": "internal\\capability\\registry.go", "source_location": "L29", "weight": 1.0}, {"source": "registry", "target": "registry_newregistry", "relation": "contains", "confidence": "EXTRACTED", "source_file": "internal\\capability\\registry.go", "source_location": "L33", "weight": 1.0}, {"source": "capability_registry", "target": "capability_registry_surface", "relation": "method", "confidence": "EXTRACTED", "source_file": "internal\\capability\\registry.go", "source_location": "L37", "weight": 1.0}, {"source": "registry", "target": "registry_applyprofilerecord", "relation": "contains", "confidence": "EXTRACTED", "source_file": "internal\\capability\\registry.go", "source_location": "L78", "weight": 1.0}, {"source": "registry", "target": "registry_clonecapabilityset", "relation": "contains", "confidence": "EXTRACTED", "source_file": "internal\\capability\\registry.go", "source_location": "L88", "weight": 1.0}, {"source": "capability_registry_surface", "target": "registry_clonecapabilityset", "relation": "calls", "confidence": "EXTRACTED", "source_file": "internal\\capability\\registry.go", "source_location": "L45", "weight": 1.0}, {"source": "capability_registry_surface", "target": "registry_applyprofilerecord", "relation": "calls", "confidence": "EXTRACTED", "source_file": "internal\\capability\\registry.go", "source_location": "L62", "weight": 1.0}]}