{"nodes": [{"id": "gemini_codec", "label": "gemini_codec.go", "file_type": "code", "source_file": "internal\\provider\\gemini_codec.go", "source_location": "L1"}, {"id": "gemini_codec_encodegeminichatrequest", "label": "EncodeGeminiChatRequest()", "file_type": "code", "source_file": "internal\\provider\\gemini_codec.go", "source_location": "L13"}, {"id": "gemini_codec_decodegeminichatrequest", "label": "DecodeGeminiChatRequest()", "file_type": "code", "source_file": "internal\\provider\\gemini_codec.go", "source_location": "L40"}, {"id": "gemini_codec_decodegeminichatresponse", "label": "DecodeGeminiChatResponse()", "file_type": "code", "source_file": "internal\\provider\\gemini_codec.go", "source_location": "L98"}, {"id": "gemini_codec_decodegeminichatstream", "label": "DecodeGeminiChatStream()", "file_type": "code", "source_file": "internal\\provider\\gemini_codec.go", "source_location": "L138"}, {"id": "gemini_codec_splitssedatapayloads", "label": "splitSSEDataPayloads()", "file_type": "code", "source_file": "internal\\provider\\gemini_codec.go", "source_location": "L182"}, {"id": "gemini_codec_mergegeminipartialfunctioncall", "label": "mergeGeminiPartialFunctionCall()", "file_type": "code", "source_file": "internal\\provider\\gemini_codec.go", "source_location": "L199"}, {"id": "gemini_codec_encodegeminichatresponse", "label": "EncodeGeminiChatResponse()", "file_type": "code", "source_file": "internal\\provider\\gemini_codec.go", "source_location": "L216"}, {"id": "gemini_codec_encodegeminimessages", "label": "encodeGeminiMessages()", "file_type": "code", "source_file": "internal\\provider\\gemini_codec.go", "source_location": "L243"}, {"id": "gemini_codec_encodegeminimessageparts", "label": "encodeGeminiMessageParts()", "file_type": "code", "source_file": "internal\\provider\\gemini_codec.go", "source_location": "L270"}, {"id": "gemini_codec_encodegeminiparts", "label": "encodeGeminiParts()", "file_type": "code", "source_file": "internal\\provider\\gemini_codec.go", "source_location": "L312"}, {"id": "gemini_codec_filtergeminimessagemetadata", "label": "filterGeminiMessageMetadata()", "file_type": "code", "source_file": "internal\\provider\\gemini_codec.go", "source_location": "L324"}, {"id": "gemini_codec_encodegeminipart", "label": "encodeGeminiPart()", "file_type": "code", "source_file": "internal\\provider\\gemini_codec.go", "source_location": "L339"}, {"id": "gemini_codec_filtergeminipartmetadata", "label": "filterGeminiPartMetadata()", "file_type": "code", "source_file": "internal\\provider\\gemini_codec.go", "source_location": "L383"}, {"id": "gemini_codec_encodegeminitoolcallpart", "label": "encodeGeminiToolCallPart()", "file_type": "code", "source_file": "internal\\provider\\gemini_codec.go", "source_location": "L398"}, {"id": "gemini_codec_decodegeminimessages", "label": "decodeGeminiMessages()", "file_type": "code", "source_file": "internal\\provider\\gemini_codec.go", "source_location": "L415"}, {"id": "gemini_codec_decodegeminirequestmessages", "label": "decodeGeminiRequestMessages()", "file_type": "code", "source_file": "internal\\provider\\gemini_codec.go", "source_location": "L427"}, {"id": "gemini_codec_decodegeminicandidate", "label": "decodeGeminiCandidate()", "file_type": "code", "source_file": "internal\\provider\\gemini_codec.go", "source_location": "L509"}, {"id": "gemini_codec_decodegeminicontent", "label": "decodeGeminiContent()", "file_type": "code", "source_file": "internal\\provider\\gemini_codec.go", "source_location": "L517"}, {"id": "gemini_codec_decodegeminisysteminstruction", "label": "decodeGeminiSystemInstruction()", "file_type": "code", "source_file": "internal\\provider\\gemini_codec.go", "source_location": "L581"}, {"id": "gemini_codec_decodegeminipart", "label": "decodeGeminiPart()", "file_type": "code", "source_file": "internal\\provider\\gemini_codec.go", "source_location": "L601"}, {"id": "gemini_codec_geminipartorder", "label": "geminiPartOrder()", "file_type": "code", "source_file": "internal\\provider\\gemini_codec.go", "source_location": "L675"}, {"id": "gemini_codec_decodegeminifunctionresponsetext", "label": "decodeGeminiFunctionResponseText()", "file_type": "code", "source_file": "internal\\provider\\gemini_codec.go", "source_location": "L682"}, {"id": "gemini_codec_resolvegeminimodel", "label": "resolveGeminiModel()", "file_type": "code", "source_file": "internal\\provider\\gemini_codec.go", "source_location": "L693"}, {"id": "gemini_codec_geminirolefromunified", "label": "geminiRoleFromUnified()", "file_type": "code", "source_file": "internal\\provider\\gemini_codec.go", "source_location": "L710"}, {"id": "gemini_codec_unifiedrolefromgemini", "label": "unifiedRoleFromGemini()", "file_type": "code", "source_file": "internal\\provider\\gemini_codec.go", "source_location": "L717"}, {"id": "gemini_codec_extractint64", "label": "extractInt64()", "file_type": "code", "source_file": "internal\\provider\\gemini_codec.go", "source_location": "L725"}], "edges": [{"source": "gemini_codec", "target": "bytes", "relation": "imports_from", "confidence": "EXTRACTED", "source_file": "internal\\provider\\gemini_codec.go", "source_location": "L4", "weight": 1.0}, {"source": "gemini_codec", "target": "json", "relation": "imports_from", "confidence": "EXTRACTED", "source_file": "internal\\provider\\gemini_codec.go", "source_location": "L5", "weight": 1.0}, {"source": "gemini_codec", "target": "fmt", "relation": "imports_from", "confidence": "EXTRACTED", "source_file": "internal\\provider\\gemini_codec.go", "source_location": "L6", "weight": 1.0}, {"source": "gemini_codec", "target": "sort", "relation": "imports_from", "confidence": "EXTRACTED", "source_file": "internal\\provider\\gemini_codec.go", "source_location": "L7", "weight": 1.0}, {"source": "gemini_codec", "target": "strings", "relation": "imports_from", "confidence": "EXTRACTED", "source_file": "internal\\provider\\gemini_codec.go", "source_location": "L8", "weight": 1.0}, {"source": "gemini_codec", "target": "domain", "relation": "imports_from", "confidence": "EXTRACTED", "source_file": "internal\\provider\\gemini_codec.go", "source_location": "L10", "weight": 1.0}, {"source": "gemini_codec", "target": "gemini_codec_encodegeminichatrequest", "relation": "contains", "confidence": "EXTRACTED", "source_file": "internal\\provider\\gemini_codec.go", "source_location": "L13", "weight": 1.0}, {"source": "gemini_codec", "target": "gemini_codec_decodegeminichatrequest", "relation": "contains", "confidence": "EXTRACTED", "source_file": "internal\\provider\\gemini_codec.go", "source_location": "L40", "weight": 1.0}, {"source": "gemini_codec", "target": "gemini_codec_decodegeminichatresponse", "relation": "contains", "confidence": "EXTRACTED", "source_file": "internal\\provider\\gemini_codec.go", "source_location": "L98", "weight": 1.0}, {"source": "gemini_codec", "target": "gemini_codec_decodegeminichatstream", "relation": "contains", "confidence": "EXTRACTED", "source_file": "internal\\provider\\gemini_codec.go", "source_location": "L138", "weight": 1.0}, {"source": "gemini_codec", "target": "gemini_codec_splitssedatapayloads", "relation": "contains", "confidence": "EXTRACTED", "source_file": "internal\\provider\\gemini_codec.go", "source_location": "L182", "weight": 1.0}, {"source": "gemini_codec", "target": "gemini_codec_mergegeminipartialfunctioncall", "relation": "contains", "confidence": "EXTRACTED", "source_file": "internal\\provider\\gemini_codec.go", "source_location": "L199", "weight": 1.0}, {"source": "gemini_codec", "target": "gemini_codec_encodegeminichatresponse", "relation": "contains", "confidence": "EXTRACTED", "source_file": "internal\\provider\\gemini_codec.go", "source_location": "L216", "weight": 1.0}, {"source": "gemini_codec", "target": "gemini_codec_encodegeminimessages", "relation": "contains", "confidence": "EXTRACTED", "source_file": "internal\\provider\\gemini_codec.go", "source_location": "L243", "weight": 1.0}, {"source": "gemini_codec", "target": "gemini_codec_encodegeminimessageparts", "relation": "contains", "confidence": "EXTRACTED", "source_file": "internal\\provider\\gemini_codec.go", "source_location": "L270", "weight": 1.0}, {"source": "gemini_codec", "target": "gemini_codec_encodegeminiparts", "relation": "contains", "confidence": "EXTRACTED", "source_file": "internal\\provider\\gemini_codec.go", "source_location": "L312", "weight": 1.0}, {"source": "gemini_codec", "target": "gemini_codec_filtergeminimessagemetadata", "relation": "contains", "confidence": "EXTRACTED", "source_file": "internal\\provider\\gemini_codec.go", "source_location": "L324", "weight": 1.0}, {"source": "gemini_codec", "target": "gemini_codec_encodegeminipart", "relation": "contains", "confidence": "EXTRACTED", "source_file": "internal\\provider\\gemini_codec.go", "source_location": "L339", "weight": 1.0}, {"source": "gemini_codec", "target": "gemini_codec_filtergeminipartmetadata", "relation": "contains", "confidence": "EXTRACTED", "source_file": "internal\\provider\\gemini_codec.go", "source_location": "L383", "weight": 1.0}, {"source": "gemini_codec", "target": "gemini_codec_encodegeminitoolcallpart", "relation": "contains", "confidence": "EXTRACTED", "source_file": "internal\\provider\\gemini_codec.go", "source_location": "L398", "weight": 1.0}, {"source": "gemini_codec", "target": "gemini_codec_decodegeminimessages", "relation": "contains", "confidence": "EXTRACTED", "source_file": "internal\\provider\\gemini_codec.go", "source_location": "L415", "weight": 1.0}, {"source": "gemini_codec", "target": "gemini_codec_decodegeminirequestmessages", "relation": "contains", "confidence": "EXTRACTED", "source_file": "internal\\provider\\gemini_codec.go", "source_location": "L427", "weight": 1.0}, {"source": "gemini_codec", "target": "gemini_codec_decodegeminicandidate", "relation": "contains", "confidence": "EXTRACTED", "source_file": "internal\\provider\\gemini_codec.go", "source_location": "L509", "weight": 1.0}, {"source": "gemini_codec", "target": "gemini_codec_decodegeminicontent", "relation": "contains", "confidence": "EXTRACTED", "source_file": "internal\\provider\\gemini_codec.go", "source_location": "L517", "weight": 1.0}, {"source": "gemini_codec", "target": "gemini_codec_decodegeminisysteminstruction", "relation": "contains", "confidence": "EXTRACTED", "source_file": "internal\\provider\\gemini_codec.go", "source_location": "L581", "weight": 1.0}, {"source": "gemini_codec", "target": "gemini_codec_decodegeminipart", "relation": "contains", "confidence": "EXTRACTED", "source_file": "internal\\provider\\gemini_codec.go", "source_location": "L601", "weight": 1.0}, {"source": "gemini_codec", "target": "gemini_codec_geminipartorder", "relation": "contains", "confidence": "EXTRACTED", "source_file": "internal\\provider\\gemini_codec.go", "source_location": "L675", "weight": 1.0}, {"source": "gemini_codec", "target": "gemini_codec_decodegeminifunctionresponsetext", "relation": "contains", "confidence": "EXTRACTED", "source_file": "internal\\provider\\gemini_codec.go", "source_location": "L682", "weight": 1.0}, {"source": "gemini_codec", "target": "gemini_codec_resolvegeminimodel", "relation": "contains", "confidence": "EXTRACTED", "source_file": "internal\\provider\\gemini_codec.go", "source_location": "L693", "weight": 1.0}, {"source": "gemini_codec", "target": "gemini_codec_geminirolefromunified", "relation": "contains", "confidence": "EXTRACTED", "source_file": "internal\\provider\\gemini_codec.go", "source_location": "L710", "weight": 1.0}, {"source": "gemini_codec", "target": "gemini_codec_unifiedrolefromgemini", "relation": "contains", "confidence": "EXTRACTED", "source_file": "internal\\provider\\gemini_codec.go", "source_location": "L717", "weight": 1.0}, {"source": "gemini_codec", "target": "gemini_codec_extractint64", "relation": "contains", "confidence": "EXTRACTED", "source_file": "internal\\provider\\gemini_codec.go", "source_location": "L725", "weight": 1.0}, {"source": "gemini_codec_encodegeminichatrequest", "target": "gemini_codec_encodegeminimessages", "relation": "calls", "confidence": "EXTRACTED", "source_file": "internal\\provider\\gemini_codec.go", "source_location": "L29", "weight": 1.0}, {"source": "gemini_codec_decodegeminichatrequest", "target": "gemini_codec_resolvegeminimodel", "relation": "calls", "confidence": "EXTRACTED", "source_file": "internal\\provider\\gemini_codec.go", "source_location": "L50", "weight": 1.0}, {"source": "gemini_codec_decodegeminichatrequest", "target": "gemini_codec_decodegeminisysteminstruction", "relation": "calls", "confidence": "EXTRACTED", "source_file": "internal\\provider\\gemini_codec.go", "source_location": "L73", "weight": 1.0}, {"source": "gemini_codec_decodegeminichatrequest", "target": "gemini_codec_decodegeminimessages", "relation": "calls", "confidence": "EXTRACTED", "source_file": "internal\\provider\\gemini_codec.go", "source_location": "L86", "weight": 1.0}, {"source": "gemini_codec_decodegeminichatresponse", "target": "gemini_codec_extractint64", "relation": "calls", "confidence": "EXTRACTED", "source_file": "internal\\provider\\gemini_codec.go", "source_location": "L112", "weight": 1.0}, {"source": "gemini_codec_decodegeminichatresponse", "target": "gemini_codec_decodegeminicandidate", "relation": "calls", "confidence": "EXTRACTED", "source_file": "internal\\provider\\gemini_codec.go", "source_location": "L130", "weight": 1.0}, {"source": "gemini_codec_decodegeminichatstream", "target": "gemini_codec_splitssedatapayloads", "relation": "calls", "confidence": "EXTRACTED", "source_file": "internal\\provider\\gemini_codec.go", "source_location": "L141", "weight": 1.0}, {"source": "gemini_codec_decodegeminichatstream", "target": "gemini_codec_decodegeminichatresponse", "relation": "calls", "confidence": "EXTRACTED", "source_file": "internal\\provider\\gemini_codec.go", "source_location": "L142", "weight": 1.0}, {"source": "gemini_codec_decodegeminichatstream", "target": "gemini_codec_mergegeminipartialfunctioncall", "relation": "calls", "confidence": "EXTRACTED", "source_file": "internal\\provider\\gemini_codec.go", "source_location": "L157", "weight": 1.0}, {"source": "gemini_codec_encodegeminichatresponse", "target": "gemini_codec_encodegeminimessageparts", "relation": "calls", "confidence": "EXTRACTED", "source_file": "internal\\provider\\gemini_codec.go", "source_location": "L222", "weight": 1.0}, {"source": "gemini_codec_encodegeminimessages", "target": "gemini_codec_encodegeminimessageparts", "relation": "calls", "confidence": "EXTRACTED", "source_file": "internal\\provider\\gemini_codec.go", "source_location": "L247", "weight": 1.0}, {"source": "gemini_codec_encodegeminimessages", "target": "gemini_codec_filtergeminimessagemetadata", "relation": "calls", "confidence": "EXTRACTED", "source_file": "internal\\provider\\gemini_codec.go", "source_location": "L256", "weight": 1.0}, {"source": "gemini_codec_encodegeminimessages", "target": "gemini_codec_geminirolefromunified", "relation": "calls", "confidence": "EXTRACTED", "source_file": "internal\\provider\\gemini_codec.go", "source_location": "L257", "weight": 1.0}, {"source": "gemini_codec_encodegeminimessageparts", "target": "gemini_codec_encodegeminipart", "relation": "calls", "confidence": "EXTRACTED", "source_file": "internal\\provider\\gemini_codec.go", "source_location": "L287", "weight": 1.0}, {"source": "gemini_codec_encodegeminimessageparts", "target": "gemini_codec_geminipartorder", "relation": "calls", "confidence": "EXTRACTED", "source_file": "internal\\provider\\gemini_codec.go", "source_location": "L291", "weight": 1.0}, {"source": "gemini_codec_encodegeminimessageparts", "target": "gemini_codec_encodegeminitoolcallpart", "relation": "calls", "confidence": "EXTRACTED", "source_file": "internal\\provider\\gemini_codec.go", "source_location": "L294", "weight": 1.0}, {"source": "gemini_codec_encodegeminiparts", "target": "gemini_codec_encodegeminipart", "relation": "calls", "confidence": "EXTRACTED", "source_file": "internal\\provider\\gemini_codec.go", "source_location": "L315", "weight": 1.0}, {"source": "gemini_codec_encodegeminipart", "target": "gemini_codec_filtergeminipartmetadata", "relation": "calls", "confidence": "EXTRACTED", "source_file": "internal\\provider\\gemini_codec.go", "source_location": "L350", "weight": 1.0}, {"source": "gemini_codec_decodegeminimessages", "target": "gemini_codec_decodegeminirequestmessages", "relation": "calls", "confidence": "EXTRACTED", "source_file": "internal\\provider\\gemini_codec.go", "source_location": "L418", "weight": 1.0}, {"source": "gemini_codec_decodegeminirequestmessages", "target": "gemini_codec_decodegeminicontent", "relation": "calls", "confidence": "EXTRACTED", "source_file": "internal\\provider\\gemini_codec.go", "source_location": "L430", "weight": 1.0}, {"source": "gemini_codec_decodegeminirequestmessages", "target": "gemini_codec_unifiedrolefromgemini", "relation": "calls", "confidence": "EXTRACTED", "source_file": "internal\\provider\\gemini_codec.go", "source_location": "L452", "weight": 1.0}, {"source": "gemini_codec_decodegeminirequestmessages", "target": "gemini_codec_decodegeminipart", "relation": "calls", "confidence": "EXTRACTED", "source_file": "internal\\provider\\gemini_codec.go", "source_location": "L465", "weight": 1.0}, {"source": "gemini_codec_decodegeminicandidate", "target": "gemini_codec_decodegeminicontent", "relation": "calls", "confidence": "EXTRACTED", "source_file": "internal\\provider\\gemini_codec.go", "source_location": "L514", "weight": 1.0}, {"source": "gemini_codec_decodegeminicontent", "target": "gemini_codec_unifiedrolefromgemini", "relation": "calls", "confidence": "EXTRACTED", "source_file": "internal\\provider\\gemini_codec.go", "source_location": "L520", "weight": 1.0}, {"source": "gemini_codec_decodegeminicontent", "target": "gemini_codec_decodegeminipart", "relation": "calls", "confidence": "EXTRACTED", "source_file": "internal\\provider\\gemini_codec.go", "source_location": "L530", "weight": 1.0}, {"source": "gemini_codec_decodegeminicontent", "target": "gemini_codec_decodegeminifunctionresponsetext", "relation": "calls", "confidence": "EXTRACTED", "source_file": "internal\\provider\\gemini_codec.go", "source_location": "L554", "weight": 1.0}, {"source": "gemini_codec_decodegeminisysteminstruction", "target": "gemini_codec_decodegeminipart", "relation": "calls", "confidence": "EXTRACTED", "source_file": "internal\\provider\\gemini_codec.go", "source_location": "L592", "weight": 1.0}]}